openhashdb/__init__.py
OpenHashDB-0.0.1.dist-info/LICENSE
OpenHashDB-0.0.1.dist-info/METADATA
OpenHashDB-0.0.1.dist-info/WHEEL
OpenHashDB-0.0.1.dist-info/top_level.txt
OpenHashDB-0.0.1.dist-info/RECORD
